mopidy_orfradio/__init__.py
mopidy_orfradio/backend.py
mopidy_orfradio/client.py
mopidy_orfradio/ext.conf
mopidy_orfradio/library.py
mopidy_orfradio/playback.py
Mopidy_ORFRadio-2.2.0.dist-info/LICENSE
Mopidy_ORFRadio-2.2.0.dist-info/METADATA
Mopidy_ORFRadio-2.2.0.dist-info/WHEEL
Mopidy_ORFRadio-2.2.0.dist-info/entry_points.txt
Mopidy_ORFRadio-2.2.0.dist-info/top_level.txt
Mopidy_ORFRadio-2.2.0.dist-info/RECORD
